geospade/__init__.py
geospade/crs.py
geospade/errors.py
geospade/raster.py
geospade/tools.py
geospade/transform.py
geospade/vector.py
geospade-0.2.4.dist-info/AUTHORS.rst
geospade-0.2.4.dist-info/LICENSE.txt
geospade-0.2.4.dist-info/METADATA
geospade-0.2.4.dist-info/WHEEL
geospade-0.2.4.dist-info/top_level.txt
geospade-0.2.4.dist-info/RECORD
