Metadata-Version: 2.1
Name: geospade
Version: 0.2.4
Summary: A place for classes and properties of raster and vector geometries and their geospatial operations alike.
Home-page: https://github.com/TUW-GEO/geospade
Author: TU Wien MRS group
Author-email: remote.sensing@geo.tuwien.ac.at
License: mit
Keywords: geospatial,raster,vector,mosaics,grids
Platform: any
Classifier: Development Status :: 4 - Beta
Classifier: License :: OSI Approved :: MIT License
Classifier: Topic :: Scientific/Engineering
Classifier: Topic :: Software Development :: Version Control :: Git
Classifier: Programming Language :: Python :: 3.6
Classifier: Natural Language :: English
Requires-Dist: numpy
Requires-Dist: pyproj
Requires-Dist: cartopy
Requires-Dist: shapely
Requires-Dist: numba
Requires-Dist: geopandas
Provides-Extra: testing
Requires-Dist: pytest ; extra == 'testing'
Requires-Dist: pytest-cov ; extra == 'testing'
